[
 {
  "custom": 1,
  "docstatus": 0,
  "doctype": "DocType Link",
  "group": "Sub Accounts",
  "hidden": 0,
  "is_child_table": 0,
  "link_doctype": "Supplier",
  "link_fieldname": "main_account",
  "modified": "2022-02-04 12:28:24.225113",
  "name": "55db421fad",
  "parent": "Supplier",
  "parent_doctype": null,
  "parentfield": "links",
  "parenttype": "Customize Form",
  "table_fieldname": null
 },
 {
  "custom": 1,
  "docstatus": 0,
  "doctype": "DocType Link",
  "group": "Sub Accounts",
  "hidden": 0,
  "is_child_table": 0,
  "link_doctype": "Customer",
  "link_fieldname": "main_account",
  "modified": "2022-01-22 11:25:05.446533",
  "name": "0b56c897c8",
  "parent": "Customer",
  "parent_doctype": null,
  "parentfield": "links",
  "parenttype": "Customize Form",
  "table_fieldname": null
 },
 {
  "custom": 1,
  "docstatus": 0,
  "doctype": "DocType Link",
  "group": "Sub Accounts",
  "hidden": 0,
  "is_child_table": 0,
  "link_doctype": "Supplier",
  "link_fieldname": "main_account",
  "modified": "2022-02-04 12:28:24.229048",
  "name": "6c455ce088",
  "parent": "Supplier",
  "parent_doctype": null,
  "parentfield": "links",
  "parenttype": "Customize Form",
  "table_fieldname": null
 },
 {
  "custom": 1,
  "docstatus": 0,
  "doctype": "DocType Link",
  "group": "Sub Accounts",
  "hidden": 0,
  "is_child_table": 0,
  "link_doctype": "Customer",
  "link_fieldname": "main_account",
  "modified": "2022-01-22 11:25:05.464029",
  "name": "048f4650ee",
  "parent": "Customer",
  "parent_doctype": null,
  "parentfield": "links",
  "parenttype": "Customize Form",
  "table_fieldname": null
 },
 {
  "custom": 1,
  "docstatus": 0,
  "doctype": "DocType Link",
  "group": "Sub Accounts",
  "hidden": 0,
  "is_child_table": 0,
  "link_doctype": "Customer",
  "link_fieldname": "main_account",
  "modified": "2022-01-22 11:25:05.467101",
  "name": "076e5022cf",
  "parent": "Customer",
  "parent_doctype": null,
  "parentfield": "links",
  "parenttype": "Customize Form",
  "table_fieldname": null
 },
 {
  "custom": 1,
  "docstatus": 0,
  "doctype": "DocType Link",
  "group": "Sub Accounts",
  "hidden": 0,
  "is_child_table": 0,
  "link_doctype": "Supplier",
  "link_fieldname": "main_account",
  "modified": "2022-02-04 12:28:24.306303",
  "name": "a528c881ec",
  "parent": "Supplier",
  "parent_doctype": null,
  "parentfield": "links",
  "parenttype": "Customize Form",
  "table_fieldname": null
 },
 {
  "custom": 1,
  "docstatus": 0,
  "doctype": "DocType Link",
  "group": "Sub Accounts",
  "hidden": 0,
  "is_child_table": 0,
  "link_doctype": "Customer",
  "link_fieldname": "main_account",
  "modified": "2022-01-22 11:25:05.470224",
  "name": "da635bf842",
  "parent": "Customer",
  "parent_doctype": null,
  "parentfield": "links",
  "parenttype": "Customize Form",
  "table_fieldname": null
 },
 {
  "custom": 1,
  "docstatus": 0,
  "doctype": "DocType Link",
  "group": "Sub Accounts",
  "hidden": 0,
  "is_child_table": 0,
  "link_doctype": "Supplier",
  "link_fieldname": "main_account",
  "modified": "2022-02-04 12:28:24.309664",
  "name": "948dfac87e",
  "parent": "Supplier",
  "parent_doctype": null,
  "parentfield": "links",
  "parenttype": "Customize Form",
  "table_fieldname": null
 },
 {
  "custom": 1,
  "docstatus": 0,
  "doctype": "DocType Link",
  "group": "Sub Accounts",
  "hidden": 0,
  "is_child_table": 0,
  "link_doctype": "Customer",
  "link_fieldname": "main_account",
  "modified": "2022-01-22 11:25:05.473164",
  "name": "b9c692f595",
  "parent": "Customer",
  "parent_doctype": null,
  "parentfield": "links",
  "parenttype": "Customize Form",
  "table_fieldname": null
 },
 {
  "custom": 1,
  "docstatus": 0,
  "doctype": "DocType Link",
  "group": "Sub Accounts",
  "hidden": 0,
  "is_child_table": 0,
  "link_doctype": "Supplier",
  "link_fieldname": "main_account",
  "modified": "2022-02-04 12:28:24.312505",
  "name": "629b01d396",
  "parent": "Supplier",
  "parent_doctype": null,
  "parentfield": "links",
  "parenttype": "Customize Form",
  "table_fieldname": null
 },
 {
  "custom": 1,
  "docstatus": 0,
  "doctype": "DocType Link",
  "group": "Sub Accounts",
  "hidden": 0,
  "is_child_table": 0,
  "link_doctype": "Customer",
  "link_fieldname": "main_account",
  "modified": "2022-01-22 11:25:05.476014",
  "name": "ba5ae75d0f",
  "parent": "Customer",
  "parent_doctype": null,
  "parentfield": "links",
  "parenttype": "Customize Form",
  "table_fieldname": null
 },
 {
  "custom": 1,
  "docstatus": 0,
  "doctype": "DocType Link",
  "group": "Sub Accounts",
  "hidden": 0,
  "is_child_table": 0,
  "link_doctype": "Supplier",
  "link_fieldname": "main_account",
  "modified": "2022-02-04 12:28:24.315314",
  "name": "1177b7556c",
  "parent": "Supplier",
  "parent_doctype": null,
  "parentfield": "links",
  "parenttype": "Customize Form",
  "table_fieldname": null
 },
 {
  "custom": 1,
  "docstatus": 0,
  "doctype": "DocType Link",
  "group": "Sub Accounts",
  "hidden": 0,
  "is_child_table": 0,
  "link_doctype": "Customer",
  "link_fieldname": "main_account",
  "modified": "2022-01-22 11:25:05.478865",
  "name": "de6028034c",
  "parent": "Customer",
  "parent_doctype": null,
  "parentfield": "links",
  "parenttype": "Customize Form",
  "table_fieldname": null
 },
 {
  "custom": 1,
  "docstatus": 0,
  "doctype": "DocType Link",
  "group": "Sub Accounts",
  "hidden": 0,
  "is_child_table": 0,
  "link_doctype": "Supplier",
  "link_fieldname": "main_account",
  "modified": "2022-02-04 12:28:24.318067",
  "name": "8884357350",
  "parent": "Supplier",
  "parent_doctype": null,
  "parentfield": "links",
  "parenttype": "Customize Form",
  "table_fieldname": null
 },
 {
  "custom": 1,
  "docstatus": 0,
  "doctype": "DocType Link",
  "group": "Sub Accounts",
  "hidden": 0,
  "is_child_table": 0,
  "link_doctype": "Customer",
  "link_fieldname": "main_account",
  "modified": "2022-01-22 11:25:05.481826",
  "name": "6298a1e35a",
  "parent": "Customer",
  "parent_doctype": null,
  "parentfield": "links",
  "parenttype": "Customize Form",
  "table_fieldname": null
 },
 {
  "custom": 1,
  "docstatus": 0,
  "doctype": "DocType Link",
  "group": "Sub Accounts",
  "hidden": 0,
  "is_child_table": 0,
  "link_doctype": "Supplier",
  "link_fieldname": "main_account",
  "modified": "2022-02-04 12:28:24.320726",
  "name": "1ae6df404b",
  "parent": "Supplier",
  "parent_doctype": null,
  "parentfield": "links",
  "parenttype": "Customize Form",
  "table_fieldname": null
 }
]